accessive/__init__.py
accessive/data_structure.py
accessive/database_ops.py
accessive/interface.py
accessive/db_builder/__init__.py
accessive/db_builder/build.py
accessive/db_builder/ensembl.py
accessive/db_builder/nextprot.py
accessive/db_builder/uniprot.py
Accessive-0.1.0.dist-info/METADATA
Accessive-0.1.0.dist-info/WHEEL
Accessive-0.1.0.dist-info/top_level.txt
Accessive-0.1.0.dist-info/RECORD
