Metadata-Version: 2.1
Name: Accessive
Version: 0.1.0
Summary: A Python library for converting between different bioinformatic accession types
Home-page: https://github.com/maxalex/accessive
Author: William Max Alexander
Author-email: accessive@alexander.bio
Classifier: Development Status :: 3 - Alpha
Classifier: Intended Audience :: Science/Research
Classifier: Topic :: Scientific/Engineering :: Bio-Informatics
Classifier: License :: OSI Approved :: MIT License
Classifier: Operating System :: OS Independent
Classifier: Programming Language :: Python :: 3
Requires-Python: >=3.6
Requires-Dist: requests
Requires-Dist: pandas (>=2.1.0)
